README.rst
setup.py
duckduckpy/__init__.py
duckduckpy/api.py
duckduckpy/core.py
duckduckpy/exception.py
duckduckpy/utils.py
duckduckpy.egg-info/PKG-INFO
duckduckpy.egg-info/SOURCES.txt
duckduckpy.egg-info/dependency_links.txt
duckduckpy.egg-info/top_level.txt
duckduckpy.egg-info/zip-safe