Metadata-Version: 1.1
Name: duckduckpy
Version: 0.2
Summary: Library for querying the instant answer API of DuckDuckGo search engine.
Home-page: https://github.com/ivankliuk/duckduckpy/
Author: Ivan Kliuk
Author-email: ivan.kliuk@gmail.com
License: MIT
Download-URL: https://github.com/ivankliuk/duckduckpy/tarball/0.2
Keywords: duckduckgo
Platform: any
Classifier: Development Status :: 2 - Pre-Alpha
Classifier: Intended Audience :: Developers
Classifier: License :: OSI Approved :: MIT License
Classifier: Operating System :: OS Independent
Classifier: Programming Language :: Python
Classifier: Programming Language :: Python :: 2
Classifier: Programming Language :: Python :: 2.6
Classifier: Programming Language :: Python :: 2.7
Classifier: Programming Language :: Python :: 3
Classifier: Programming Language :: Python :: 3.3
Classifier: Programming Language :: Python :: 3.4
Classifier: Programming Language :: Python :: 3.5
Classifier: Topic :: Internet :: WWW/HTTP :: Indexing/Search
